UnderstandingEcmascript6Zhongwenban/README.md
UnderstandingEcmascript6Zhongwenban/__init__.py
UnderstandingEcmascript6Zhongwenban/__main__.py
UnderstandingEcmascript6Zhongwenban/file.epub
UnderstandingEcmascript6Zhongwenban/index.html
UnderstandingEcmascript6Zhongwenban/css/__init__.py
UnderstandingEcmascript6Zhongwenban/css/annotations.css
UnderstandingEcmascript6Zhongwenban/css/main.css
UnderstandingEcmascript6Zhongwenban/css/normalize.css
UnderstandingEcmascript6Zhongwenban/css/popup.css
UnderstandingEcmascript6Zhongwenban/font/__init__.py
UnderstandingEcmascript6Zhongwenban/font/fontello.eot
UnderstandingEcmascript6Zhongwenban/font/fontello.svg
UnderstandingEcmascript6Zhongwenban/font/fontello.ttf
UnderstandingEcmascript6Zhongwenban/font/fontello.woff
UnderstandingEcmascript6Zhongwenban/img/__init__.py
UnderstandingEcmascript6Zhongwenban/img/annotator-glyph-sprite.png
UnderstandingEcmascript6Zhongwenban/img/annotator-icon-sprite.png
UnderstandingEcmascript6Zhongwenban/img/apple-touch-icon.png
UnderstandingEcmascript6Zhongwenban/img/cancelfullscreen.png
UnderstandingEcmascript6Zhongwenban/img/close.png
UnderstandingEcmascript6Zhongwenban/img/fullscreen.png
UnderstandingEcmascript6Zhongwenban/img/loader.gif
UnderstandingEcmascript6Zhongwenban/img/menu-icon.png
UnderstandingEcmascript6Zhongwenban/img/save.png
UnderstandingEcmascript6Zhongwenban/img/saved.png
UnderstandingEcmascript6Zhongwenban/img/settings-s.png
UnderstandingEcmascript6Zhongwenban/img/settings.png
UnderstandingEcmascript6Zhongwenban/img/star.png
UnderstandingEcmascript6Zhongwenban/js/__init__.py
UnderstandingEcmascript6Zhongwenban/js/epub.js
UnderstandingEcmascript6Zhongwenban/js/epub.min.js
UnderstandingEcmascript6Zhongwenban/js/epub.min.map
UnderstandingEcmascript6Zhongwenban/js/hooks.min.js
UnderstandingEcmascript6Zhongwenban/js/hooks.min.map
UnderstandingEcmascript6Zhongwenban/js/reader.js
UnderstandingEcmascript6Zhongwenban/js/reader.js.map
UnderstandingEcmascript6Zhongwenban/js/reader.min.js
understanding_ecmascript_6_zhongwenban-2024.3.2.0.dist-info/METADATA
understanding_ecmascript_6_zhongwenban-2024.3.2.0.dist-info/WHEEL
understanding_ecmascript_6_zhongwenban-2024.3.2.0.dist-info/entry_points.txt
understanding_ecmascript_6_zhongwenban-2024.3.2.0.dist-info/top_level.txt
understanding_ecmascript_6_zhongwenban-2024.3.2.0.dist-info/RECORD
